arguments.py
cli.py
config.py
constants.py
logger.py
prompt.py
review.py
util.py
version.py
prompts/advance.md
prompts/dba.md
prompts/default.md
prompts/omr.md
prompts/internal/consolidate_reviews.md
prompts/internal/split_code.md
prompts/internal/stage1_intent_and_sanity_check.md
prompts/internal/stage2_core_practices_and_robustness.md
prompts/internal/stage3_systemic_risk_and_advanced_review.md
prompts/internal/stage4_final_report_generation.md
services/__init__.py
services/confluence.py
services/gemini.py
services/gitlab.py
services/jira.py
v_magic_code_review-0.2.5.dist-info/METADATA
v_magic_code_review-0.2.5.dist-info/WHEEL
v_magic_code_review-0.2.5.dist-info/entry_points.txt
v_magic_code_review-0.2.5.dist-info/top_level.txt
v_magic_code_review-0.2.5.dist-info/RECORD
