Metadata-Version: 2.4
Name: v-magic-code-review
Version: 0.2.5
Author-email: Howie Peng <howie.peng@veeva.com>
Requires-Python: <3.14,>=3.12
Requires-Dist: atlassian-python-api==4.0.7
Requires-Dist: gemini-webapi==1.15.2
Requires-Dist: browser-cookie3==0.20.1
Requires-Dist: python-gitlab==6.3.0
Requires-Dist: beautifulsoup4==4.13.5
Requires-Dist: markdownify==1.2.0
Requires-Dist: lxml<6.0.0,>=5.4.0
Requires-Dist: termcolor<2.4.0,>=2.2.0
Requires-Dist: pyperclip<2.0.0,>=1.9.0
Requires-Dist: rich<15.0.0,>=14.0.0
Requires-Dist: yaspin<4.0.0,>=3.1.0
Requires-Dist: tiktoken==0.11.0
Requires-Dist: update-checker>=0.18.0
